del_msh-0.1.39.dist-info/METADATA
del_msh-0.1.39.dist-info/WHEEL
del_msh/BVH.py
del_msh/BlendShape.py
del_msh/DeformMLS.py
del_msh/KdTree.py
del_msh/PolyLoop.py
del_msh/PolygonMesh.py
del_msh/Tet.py
del_msh/Tri.py
del_msh/TriMesh.py
del_msh/WavefrontObj.py
del_msh/__init__.py
del_msh/del_msh.cpython-313-darwin.so
del_msh-0.1.39.dist-info/RECORD
