Metadata-Version: 2.4
Name: del-msh
Version: 0.1.39
Classifier: Programming Language :: Rust
Classifier: Programming Language :: Python :: Implementation :: CPython
Classifier: Programming Language :: Python :: Implementation :: PyPy
Requires-Dist: numpy
License: MIT
Requires-Python: >=3.7
